Metadata-Version: 2.1
Name: atd-kits-util-dev
Version: 0.0.2
Summary: Python utilities for interacting with KITS, an advanced transportation management application.
Home-page: https://github.com/cityofaustin/atd-data-utilities/tree/master/atd-kits-util
Author: City of Austin
Author-email: transportation.data@austintexas.gov
License: UNKNOWN
Platform: UNKNOWN
Classifier: Programming Language :: Python :: 3
Classifier: License :: Public Domain
Classifier: Operating System :: OS Independent
Classifier: Development Status :: 4 - Beta
Requires-Dist: arrow
Requires-Dist: pymssql
